text4gcn/__init__.py
text4gcn/__main__.py
text4gcn/builder/__init__.py
text4gcn/builder/constituency_parsing_adj.py
text4gcn/builder/cosine_similarity_adj.py
text4gcn/builder/dependency_parsing_adj.py
text4gcn/builder/embedding_adj.py
text4gcn/builder/frequency_adj.py
text4gcn/builder/linguistic_inquiry_adj.py
text4gcn/builder/pipeline.py
text4gcn/datasets/__init__.py
text4gcn/datasets/data.py
text4gcn/models/__init__.py
text4gcn/models/builder.py
text4gcn/models/gnn.py
text4gcn/models/layers.py
text4gcn/models/model.py
text4gcn/models/train_eval.py
text4gcn/models/utils.py
text4gcn/modules/__init__.py
text4gcn/modules/adjacency.py
text4gcn/modules/clean_data.py
text4gcn/modules/file_ops.py
text4gcn/modules/log_time_process.py
text4gcn/modules/logger.py
text4gcn/modules/node_features.py
text4gcn/modules/prepare_words.py
text4gcn/modules/shuffle_data.py
text4gcn/modules/utils.py
text4gcn/modules/word_processor.py
text4gcn/modules/textvec/__init__.py
text4gcn/modules/textvec/liwc.py
text4gcn/modules/textvec/word_features.py
text4gcn/preprocess/__init__.py
text4gcn/preprocess/config.py
text4gcn/preprocess/pipeline.py
text4gcn-1.0.0.dist-info/LICENSE
text4gcn-1.0.0.dist-info/METADATA
text4gcn-1.0.0.dist-info/WHEEL
text4gcn-1.0.0.dist-info/top_level.txt
text4gcn-1.0.0.dist-info/RECORD
