Metadata-Version: 2.1
Name: text4gcn
Version: 1.0.0
Summary: A library for building text graphs for the application of Graph Neural Networks (GNN), in the context of text classification in natural language processing
Home-page: https://github.com/vitormeriat/text4gcn
Author: Vitor Meriat
Author-email: vitormeriat@gmail.com
License: MIT
Keywords: tgcn,gcn,gnn,nlp,text_classification,text_graph
Platform: manylinux1_x86_64
Classifier: License :: OSI Approved :: MIT License
Classifier: Programming Language :: Python :: 3.8
Classifier: Operating System :: OS Independent
License-File: LICENSE
Requires-Dist: gensim (>=4.1.2)
Requires-Dist: nltk (>=3.5)
Requires-Dist: scikit-learn (>=0.23.2)
Requires-Dist: stanfordcorenlp (>=3.9.1.1)
Requires-Dist: tabulate (>=0.8.9)
Requires-Dist: matplotlib (>=3.1.1)
Requires-Dist: torch (>=1.11.0)
